calamari/__init__.py
calamari/engine/__init__.py
calamari/engine/config.py
calamari/engine/engine.py
calamari/interfaces/__init__.py
calamari/interfaces/irc_interface.py
calamari/interfaces/xmpp.py
Calamari-1.0.3.dist-info/DESCRIPTION.rst
Calamari-1.0.3.dist-info/METADATA
Calamari-1.0.3.dist-info/metadata.json
Calamari-1.0.3.dist-info/RECORD
Calamari-1.0.3.dist-info/top_level.txt
Calamari-1.0.3.dist-info/WHEEL
