Metadata-Version: 2.0
Name: Calamari
Version: 1.0.3
Summary: A simple, easy, and extensible chat bot
Home-page: https://github.com/drcauley/calamari
Author: Danial Ray Cauley
Author-email: girdot@gmail.com
License: MIT
Keywords: chat bot jabber xmpp irc
Platform: UNKNOWN
Classifier: Development Status :: 4 - Beta
Classifier: Intended Audience :: Developers
Classifier: License :: OSI Approved :: MIT License
Classifier: Programming Language :: Python :: 2.7
Requires-Dist: werkzeug
Requires-Dist: sleekxmpp
Requires-Dist: twisted
Requires-Dist: pyopenssl
Requires-Dist: service-identity
